<annotation>
	<folder>SHOPPE2017</folder>
	<filename>0405.jpg</filename>
	<source>
		<database>The SHOPPE2017 Database</database>
	</source>
	<size>
		<width>550</width>
		<height>833</height>
		<depth>3</depth>
	</size>
	<segmented>0</segmented>
	<object>
		<name>bag</name>
		<pose>Unspecified</pose>
		<truncated>0</truncated>
		<difficult>0</difficult>
		<bndbox>
			<xmin>112</xmin>
			<ymin>296</ymin>
			<xmax>255</xmax>
			<ymax>502</ymax>
		</bndbox>
	</object>
	<object>
		<name>belt</name>
		<pose>Unspecified</pose>
		<truncated>0</truncated>
		<difficult>0</difficult>
		<bndbox>
			<xmin>232</xmin>
			<ymin>309</ymin>
			<xmax>350</xmax>
			<ymax>335</ymax>
		</bndbox>
	</object>
	<object>
		<name>shoes</name>
		<pose>Unspecified</pose>
		<truncated>0</truncated>
		<difficult>0</difficult>
		<bndbox>
			<xmin>235</xmin>
			<ymin>700</ymin>
			<xmax>330</xmax>
			<ymax>805</ymax>
		</bndbox>
	</object>
	<object>
		<name>skin</name>
		<pose>Unspecified</pose>
		<truncated>0</truncated>
		<difficult>0</difficult>
		<bndbox>
			<xmin>172</xmin>
			<ymin>186</ymin>
			<xmax>238</xmax>
			<ymax>330</ymax>
		</bndbox>
	</object>
	<object>
		<name>skin</name>
		<pose>Unspecified</pose>
		<truncated>0</truncated>
		<difficult>0</difficult>
		<bndbox>
			<xmin>218</xmin>
			<ymin>493</ymin>
			<xmax>283</xmax>
			<ymax>709</ymax>
		</bndbox>
	</object>
	<object>
		<name>skin</name>
		<pose>Unspecified</pose>
		<truncated>0</truncated>
		<difficult>0</difficult>
		<bndbox>
			<xmin>271</xmin>
			<ymin>72</ymin>
			<xmax>347</xmax>
			<ymax>234</ymax>
		</bndbox>
	</object>
	<object>
		<name>skin</name>
		<pose>Unspecified</pose>
		<truncated>0</truncated>
		<difficult>0</difficult>
		<bndbox>
			<xmin>288</xmin>
			<ymin>517</ymin>
			<xmax>342</xmax>
			<ymax>701</ymax>
		</bndbox>
	</object>
	<object>
		<name>skin</name>
		<pose>Unspecified</pose>
		<truncated>0</truncated>
		<difficult>0</difficult>
		<bndbox>
			<xmin>356</xmin>
			<ymin>182</ymin>
			<xmax>392</xmax>
			<ymax>473</ymax>
		</bndbox>
	</object>
	<object>
		<name>dress</name>
		<pose>Unspecified</pose>
		<truncated>0</truncated>
		<difficult>0</difficult>
		<bndbox>
			<xmin>195</xmin>
			<ymin>316</ymin>
			<xmax>358</xmax>
			<ymax>553</ymax>
		</bndbox>
	</object>
	<object>
		<name>dress</name>
		<pose>Unspecified</pose>
		<truncated>0</truncated>
		<difficult>0</difficult>
		<bndbox>
			<xmin>226</xmin>
			<ymin>176</ymin>
			<xmax>367</xmax>
			<ymax>328</ymax>
		</bndbox>
	</object>
	<object>
		<name>sunglasses</name>
		<pose>Unspecified</pose>
		<truncated>0</truncated>
		<difficult>0</difficult>
		<bndbox>
			<xmin>276</xmin>
			<ymin>95</ymin>
			<xmax>299</xmax>
			<ymax>118</ymax>
		</bndbox>
	</object>
	<object>
		<name>sunglasses</name>
		<pose>Unspecified</pose>
		<truncated>0</truncated>
		<difficult>0</difficult>
		<bndbox>
			<xmin>309</xmin>
			<ymin>84</ymin>
			<xmax>338</xmax>
			<ymax>116</ymax>
		</bndbox>
	</object>
	<object>
		<name>hair</name>
		<pose>Unspecified</pose>
		<truncated>0</truncated>
		<difficult>0</difficult>
		<bndbox>
			<xmin>244</xmin>
			<ymin>48</ymin>
			<xmax>336</xmax>
			<ymax>234</ymax>
		</bndbox>
	</object>
	<object>
		<name>hair</name>
		<pose>Unspecified</pose>
		<truncated>0</truncated>
		<difficult>0</difficult>
		<bndbox>
			<xmin>316</xmin>
			<ymin>122</ymin>
			<xmax>360</xmax>
			<ymax>206</ymax>
		</bndbox>
	</object>
	<object>
		<name>hair</name>
		<pose>Unspecified</pose>
		<truncated>0</truncated>
		<difficult>0</difficult>
		<bndbox>
			<xmin>331</xmin>
			<ymin>96</ymin>
			<xmax>338</xmax>
			<ymax>108</ymax>
		</bndbox>
	</object>
</annotation>