<annotation>
	<folder>SHOPPE2017</folder>
	<filename>0473.jpg</filename>
	<source>
		<database>The SHOPPE2017 Database</database>
	</source>
	<size>
		<width>550</width>
		<height>831</height>
		<depth>3</depth>
	</size>
	<segmented>0</segmented>
	<object>
		<name>bag</name>
		<pose>Unspecified</pose>
		<truncated>0</truncated>
		<difficult>0</difficult>
		<bndbox>
			<xmin>274</xmin>
			<ymin>422</ymin>
			<xmax>424</xmax>
			<ymax>618</ymax>
		</bndbox>
	</object>
	<object>
		<name>belt</name>
		<pose>Unspecified</pose>
		<truncated>0</truncated>
		<difficult>0</difficult>
		<bndbox>
			<xmin>200</xmin>
			<ymin>302</ymin>
			<xmax>261</xmax>
			<ymax>327</ymax>
		</bndbox>
	</object>
	<object>
		<name>shoes</name>
		<pose>Unspecified</pose>
		<truncated>0</truncated>
		<difficult>0</difficult>
		<bndbox>
			<xmin>223</xmin>
			<ymin>763</ymin>
			<xmax>272</xmax>
			<ymax>794</ymax>
		</bndbox>
	</object>
	<object>
		<name>shoes</name>
		<pose>Unspecified</pose>
		<truncated>0</truncated>
		<difficult>0</difficult>
		<bndbox>
			<xmin>324</xmin>
			<ymin>765</ymin>
			<xmax>383</xmax>
			<ymax>792</ymax>
		</bndbox>
	</object>
	<object>
		<name>skin</name>
		<pose>Unspecified</pose>
		<truncated>0</truncated>
		<difficult>0</difficult>
		<bndbox>
			<xmin>162</xmin>
			<ymin>450</ymin>
			<xmax>175</xmax>
			<ymax>470</ymax>
		</bndbox>
	</object>
	<object>
		<name>skin</name>
		<pose>Unspecified</pose>
		<truncated>0</truncated>
		<difficult>0</difficult>
		<bndbox>
			<xmin>205</xmin>
			<ymin>48</ymin>
			<xmax>275</xmax>
			<ymax>170</ymax>
		</bndbox>
	</object>
	<object>
		<name>skin</name>
		<pose>Unspecified</pose>
		<truncated>0</truncated>
		<difficult>0</difficult>
		<bndbox>
			<xmin>315</xmin>
			<ymin>422</ymin>
			<xmax>326</xmax>
			<ymax>436</ymax>
		</bndbox>
	</object>
	<object>
		<name>skin</name>
		<pose>Unspecified</pose>
		<truncated>0</truncated>
		<difficult>0</difficult>
		<bndbox>
			<xmin>332</xmin>
			<ymin>422</ymin>
			<xmax>359</xmax>
			<ymax>444</ymax>
		</bndbox>
	</object>
	<object>
		<name>coat</name>
		<pose>Unspecified</pose>
		<truncated>0</truncated>
		<difficult>0</difficult>
		<bndbox>
			<xmin>132</xmin>
			<ymin>161</ymin>
			<xmax>214</xmax>
			<ymax>466</ymax>
		</bndbox>
	</object>
	<object>
		<name>coat</name>
		<pose>Unspecified</pose>
		<truncated>0</truncated>
		<difficult>0</difficult>
		<bndbox>
			<xmin>249</xmin>
			<ymin>125</ymin>
			<xmax>368</xmax>
			<ymax>426</ymax>
		</bndbox>
	</object>
	<object>
		<name>sunglasses</name>
		<pose>Unspecified</pose>
		<truncated>0</truncated>
		<difficult>0</difficult>
		<bndbox>
			<xmin>204</xmin>
			<ymin>76</ymin>
			<xmax>258</xmax>
			<ymax>105</ymax>
		</bndbox>
	</object>
	<object>
		<name>hair</name>
		<pose>Unspecified</pose>
		<truncated>0</truncated>
		<difficult>0</difficult>
		<bndbox>
			<xmin>164</xmin>
			<ymin>25</ymin>
			<xmax>280</xmax>
			<ymax>262</ymax>
		</bndbox>
	</object>
	<object>
		<name>top</name>
		<pose>Unspecified</pose>
		<truncated>0</truncated>
		<difficult>0</difficult>
		<bndbox>
			<xmin>203</xmin>
			<ymin>140</ymin>
			<xmax>278</xmax>
			<ymax>313</ymax>
		</bndbox>
	</object>
	<object>
		<name>pants</name>
		<pose>Unspecified</pose>
		<truncated>0</truncated>
		<difficult>0</difficult>
		<bndbox>
			<xmin>172</xmin>
			<ymin>320</ymin>
			<xmax>320</xmax>
			<ymax>768</ymax>
		</bndbox>
	</object>
	<object>
		<name>pants</name>
		<pose>Unspecified</pose>
		<truncated>0</truncated>
		<difficult>0</difficult>
		<bndbox>
			<xmin>274</xmin>
			<ymin>524</ymin>
			<xmax>289</xmax>
			<ymax>550</ymax>
		</bndbox>
	</object>
	<object>
		<name>pants</name>
		<pose>Unspecified</pose>
		<truncated>0</truncated>
		<difficult>0</difficult>
		<bndbox>
			<xmin>286</xmin>
			<ymin>608</ymin>
			<xmax>392</xmax>
			<ymax>785</ymax>
		</bndbox>
	</object>
</annotation>